setup.py
prob_dsnd_distributions/Binomialdistribution.py
prob_dsnd_distributions/Gaussiandistribution.py
prob_dsnd_distributions/Generaldistribution.py
prob_dsnd_distributions/__init__.py
prob_dsnd_distributions.egg-info/PKG-INFO
prob_dsnd_distributions.egg-info/SOURCES.txt
prob_dsnd_distributions.egg-info/dependency_links.txt
prob_dsnd_distributions.egg-info/not-zip-safe
prob_dsnd_distributions.egg-info/top_level.txt