Metadata-Version: 1.0
Name: prob-dsnd-distributions
Version: 1.0
Summary: Gaussian and Binomial distributions
Home-page: UNKNOWN
Author: Sarvaswa Tandon
Author-email: savvy235@gmail.com
License: UNKNOWN
Platform: UNKNOWN
